pfapack/__init__.py
pfapack/ctypes.py
pfapack/libcpfapack.so
pfapack/pfaffian.py
pfapack_batched-0.0.2.dist-info/LICENSE
pfapack_batched-0.0.2.dist-info/METADATA
pfapack_batched-0.0.2.dist-info/WHEEL
pfapack_batched-0.0.2.dist-info/top_level.txt
pfapack_batched-0.0.2.dist-info/RECORD
