Metadata-Version: 2.1
Name: pfapack-batched
Version: 0.0.2
Summary: Efficient numerical computation of the Pfaffian for dense and banded skew-symmetric matrices (batched version).
Home-page: https://github.com/yourusername/pfapack-batched
Author: Your Name
Author-email: your.email@example.com
License: MIT
Classifier: Intended Audience :: Science/Research
Classifier: Operating System :: OS Independent
Classifier: Programming Language :: Python :: 3
Classifier: Topic :: Scientific/Engineering
Classifier: License :: OSI Approved :: MIT License
Classifier: Programming Language :: Python :: 3.9
Requires-Python: >=3.9
License-File: LICENSE
Requires-Dist: scipy
Requires-Dist: numpy
Requires-Dist: Cython
Requires-Dist: setuptools
Provides-Extra: dev
Requires-Dist: pre-commit; extra == "dev"
Provides-Extra: docs
Requires-Dist: sphinx; extra == "docs"
Requires-Dist: sphinx-rtd-theme; extra == "docs"
Requires-Dist: m2r; extra == "docs"
Requires-Dist: sphinxcontrib.apidoc; extra == "docs"
Provides-Extra: testing
Requires-Dist: pytest; extra == "testing"
Requires-Dist: pytest-cov; extra == "testing"
Requires-Dist: pytest-mypy; extra == "testing"
Requires-Dist: tox; extra == "testing"
